hourly/__init__.py
hourly/hourly.py
hourly/cli/__init__.py
hourly/cli/main.py
hourly/cli/conf/config.yaml
hourly/cli/conf/hourly.yaml
hourly/cli/conf/invoice/btcpay.yaml
hourly/cli/conf/invoice/stripe.yaml
hourly/invoice/__init__.py
hourly/invoice/btcpay.py
hourly/invoice/stripe.py
hourly-0.3.19.dist-info/LICENSE
hourly-0.3.19.dist-info/METADATA
hourly-0.3.19.dist-info/WHEEL
hourly-0.3.19.dist-info/entry_points.txt
hourly-0.3.19.dist-info/top_level.txt
hourly-0.3.19.dist-info/RECORD
