Metadata-Version: 2.1
Name: hourly
Version: 0.3.19
Summary: A time tracking tool for git repos
Home-page: https://github.com/asherp/hourly
Author: Asher Pembroke
Author-email: apembroke@gmail.com
License: Apache License Version 2.0
Platform: UNKNOWN
Classifier: Programming Language :: Python :: 3.6
Classifier: Operating System :: OS Independent
Classifier: License :: OSI Approved :: Apache Software License
Requires-Python: >=3.6
License-File: LICENSE
Requires-Dist: pandas
Requires-Dist: gitpython (==3.1.18)
Requires-Dist: plotly (==5.2.1)
Requires-Dist: hydra-core (==0.11.3)
